ShapKa/__init__.py
ShapKa/cooperativegame.py
ShapKa/kanomodel.py
ShapKa/payoff.py
tests/__init__.py
tests/test_ShapKa.py
tests/.ipynb_checkpoints/__init__-checkpoint.py
tests/.ipynb_checkpoints/test_ShapKa-checkpoint.py
ShapKa-1.1.1.dist-info/AUTHORS.rst
ShapKa-1.1.1.dist-info/LICENSE
ShapKa-1.1.1.dist-info/METADATA
ShapKa-1.1.1.dist-info/WHEEL
ShapKa-1.1.1.dist-info/top_level.txt
ShapKa-1.1.1.dist-info/RECORD
