Metadata-Version: 2.1
Name: ShapKa
Version: 1.1.1
Summary: Key Satisfaction Drivers Analysis based on Shapley values and Kano model
Home-page: https://github.com/auyanik/ShapKa
Author: Ayhan UYANIK
Author-email: uyanik.ayhan@gmail.com
License: MIT license
Keywords: ShapKa
Platform: UNKNOWN
Classifier: Programming Language :: Python :: 3
Classifier: License :: OSI Approved :: MIT License
Classifier: Operating System :: Unix
Classifier: Development Status :: 5 - Production/Stable
Requires-Python: >=3.7.*
